stechuhr/__init__.py
stechuhr/errors.py
stechuhr/logbooks.py
stechuhr/py.typed
stechuhr-0.1.0.dist-info/METADATA
stechuhr-0.1.0.dist-info/WHEEL
stechuhr-0.1.0.dist-info/entry_points.txt
stechuhr-0.1.0.dist-info/licenses/LICENSE.txt
stechuhr-0.1.0.dist-info/RECORD
