Metadata-Version: 2.4
Name: stechuhr
Version: 0.1.0
Summary: Add your description here
Author-email: Lukas Grassauer <lukas@grassauer.eu>
License-File: LICENSE.txt
Requires-Python: >=3.13
Requires-Dist: cel-python<=0.2.0,>=0.2.0
